Metadata-Version: 2.1
Name: filewrap
Version: 1.1.6
Summary: Python package for file/directory/archive management.
Home-page: https://github.com/CodeConfidant/filewrap-os
Author: Drew Hainer
Author-email: codeconfidant@gmail.com
License: MIT
Platform: Windows
Platform: Linux
License-File: LICENSE
